{
  "openapi": "3.0.1",
  "info": {
    "title": "Firdous_Portfolio",
    "version": "1.0"
  },
  "paths": {
    "/api/ContactMessages": {
      "get": {
        "tags": [
          "ContactMessages"
        ],
        "responses": {
          "200": {
            "description": "OK",
            "content": {
              "text/plain": {
                "schema": {
                  "type": "array",
                  "items": {
                    "$ref": "#/components/schemas/ContactMessage"
                  }
                }
              },
              "application/json": {
                "schema": {
                  "type": "array",
                  "items": {
                    "$ref": "#/components/schemas/ContactMessage"
                  }
                }
              },
              "text/json": {
                "schema": {
                  "type": "array",
                  "items": {
                    "$ref": "#/components/schemas/ContactMessage"
                  }
                }
              }
            }
          }
        }
      },
      "post": {
        "tags": [
          "ContactMessages"
        ],
        "requestBody": {
          "content": {
            "application/json": {
              "schema": {
                "$ref": "#/components/schemas/ContactMessage"
              }
            },
            "text/json": {
              "schema": {
                "$ref": "#/components/schemas/ContactMessage"
              }
            },
            "application/*+json": {
              "schema": {
                "$ref": "#/components/schemas/ContactMessage"
              }
            }
          }
        },
        "responses": {
          "200": {
            "description": "OK",
            "content": {
              "text/plain": {
                "schema": {
                  "$ref": "#/components/schemas/ContactMessage"
                }
              },
              "application/json": {
                "schema": {
                  "$ref": "#/components/schemas/ContactMessage"
                }
              },
              "text/json": {
                "schema": {
                  "$ref": "#/components/schemas/ContactMessage"
                }
              }
            }
          }
        }
      }
    },
    "/api/ContactMessages/{id}": {
      "get": {
        "tags": [
          "ContactMessages"
        ],
        "parameters": [
          {
            "name": "id",
            "in": "path",
            "required": true,
            "schema": {
              "type": "integer",
              "format": "int32"
            }
          }
        ],
        "responses": {
          "200": {
            "description": "OK",
            "content": {
              "text/plain": {
                "schema": {
                  "$ref": "#/components/schemas/ContactMessage"
                }
              },
              "application/json": {
                "schema": {
                  "$ref": "#/components/schemas/ContactMessage"
                }
              },
              "text/json": {
                "schema": {
                  "$ref": "#/components/schemas/ContactMessage"
                }
              }
            }
          }
        }
      },
      "put": {
        "tags": [
          "ContactMessages"
        ],
        "parameters": [
          {
            "name": "id",
            "in": "path",
            "required": true,
            "schema": {
              "type": "integer",
              "format": "int32"
            }
          }
        ],
        "requestBody": {
          "content": {
            "application/json": {
              "schema": {
                "$ref": "#/components/schemas/ContactMessage"
              }
            },
            "text/json": {
              "schema": {
                "$ref": "#/components/schemas/ContactMessage"
              }
            },
            "application/*+json": {
              "schema": {
                "$ref": "#/components/schemas/ContactMessage"
              }
            }
          }
        },
        "responses": {
          "200": {
            "description": "OK"
          }
        }
      },
      "delete": {
        "tags": [
          "ContactMessages"
        ],
        "parameters": [
          {
            "name": "id",
            "in": "path",
            "required": true,
            "schema": {
              "type": "integer",
              "format": "int32"
            }
          }
        ],
        "responses": {
          "200": {
            "description": "OK"
          }
        }
      }
    },
    "/api/Educations": {
      "get": {
        "tags": [
          "Educations"
        ],
        "responses": {
          "200": {
            "description": "OK",
            "content": {
              "text/plain": {
                "schema": {
                  "type": "array",
                  "items": {
                    "$ref": "#/components/schemas/Education"
                  }
                }
              },
              "application/json": {
                "schema": {
                  "type": "array",
                  "items": {
                    "$ref": "#/components/schemas/Education"
                  }
                }
              },
              "text/json": {
                "schema": {
                  "type": "array",
                  "items": {
                    "$ref": "#/components/schemas/Education"
                  }
                }
              }
            }
          }
        }
      },
      "post": {
        "tags": [
          "Educations"
        ],
        "requestBody": {
          "content": {
            "application/json": {
              "schema": {
                "$ref": "#/components/schemas/Education"
              }
            },
            "text/json": {
              "schema": {
                "$ref": "#/components/schemas/Education"
              }
            },
            "application/*+json": {
              "schema": {
                "$ref": "#/components/schemas/Education"
              }
            }
          }
        },
        "responses": {
          "200": {
            "description": "OK",
            "content": {
              "text/plain": {
                "schema": {
                  "$ref": "#/components/schemas/Education"
                }
              },
              "application/json": {
                "schema": {
                  "$ref": "#/components/schemas/Education"
                }
              },
              "text/json": {
                "schema": {
                  "$ref": "#/components/schemas/Education"
                }
              }
            }
          }
        }
      }
    },
    "/api/Educations/{id}": {
      "get": {
        "tags": [
          "Educations"
        ],
        "parameters": [
          {
            "name": "id",
            "in": "path",
            "required": true,
            "schema": {
              "type": "integer",
              "format": "int32"
            }
          }
        ],
        "responses": {
          "200": {
            "description": "OK",
            "content": {
              "text/plain": {
                "schema": {
                  "$ref": "#/components/schemas/Education"
                }
              },
              "application/json": {
                "schema": {
                  "$ref": "#/components/schemas/Education"
                }
              },
              "text/json": {
                "schema": {
                  "$ref": "#/components/schemas/Education"
                }
              }
            }
          }
        }
      },
      "put": {
        "tags": [
          "Educations"
        ],
        "parameters": [
          {
            "name": "id",
            "in": "path",
            "required": true,
            "schema": {
              "type": "integer",
              "format": "int32"
            }
          }
        ],
        "requestBody": {
          "content": {
            "application/json": {
              "schema": {
                "$ref": "#/components/schemas/Education"
              }
            },
            "text/json": {
              "schema": {
                "$ref": "#/components/schemas/Education"
              }
            },
            "application/*+json": {
              "schema": {
                "$ref": "#/components/schemas/Education"
              }
            }
          }
        },
        "responses": {
          "200": {
            "description": "OK"
          }
        }
      },
      "delete": {
        "tags": [
          "Educations"
        ],
        "parameters": [
          {
            "name": "id",
            "in": "path",
            "required": true,
            "schema": {
              "type": "integer",
              "format": "int32"
            }
          }
        ],
        "responses": {
          "200": {
            "description": "OK"
          }
        }
      }
    },
    "/api/Experiences": {
      "get": {
        "tags": [
          "Experiences"
        ],
        "responses": {
          "200": {
            "description": "OK",
            "content": {
              "text/plain": {
                "schema": {
                  "type": "array",
                  "items": {
                    "$ref": "#/components/schemas/Experience"
                  }
                }
              },
              "application/json": {
                "schema": {
                  "type": "array",
                  "items": {
                    "$ref": "#/components/schemas/Experience"
                  }
                }
              },
              "text/json": {
                "schema": {
                  "type": "array",
                  "items": {
                    "$ref": "#/components/schemas/Experience"
                  }
                }
              }
            }
          }
        }
      },
      "post": {
        "tags": [
          "Experiences"
        ],
        "requestBody": {
          "content": {
            "application/json": {
              "schema": {
                "$ref": "#/components/schemas/Experience"
              }
            },
            "text/json": {
              "schema": {
                "$ref": "#/components/schemas/Experience"
              }
            },
            "application/*+json": {
              "schema": {
                "$ref": "#/components/schemas/Experience"
              }
            }
          }
        },
        "responses": {
          "200": {
            "description": "OK",
            "content": {
              "text/plain": {
                "schema": {
                  "$ref": "#/components/schemas/Experience"
                }
              },
              "application/json": {
                "schema": {
                  "$ref": "#/components/schemas/Experience"
                }
              },
              "text/json": {
                "schema": {
                  "$ref": "#/components/schemas/Experience"
                }
              }
            }
          }
        }
      }
    },
    "/api/Experiences/{id}": {
      "get": {
        "tags": [
          "Experiences"
        ],
        "parameters": [
          {
            "name": "id",
            "in": "path",
            "required": true,
            "schema": {
              "type": "integer",
              "format": "int32"
            }
          }
        ],
        "responses": {
          "200": {
            "description": "OK",
            "content": {
              "text/plain": {
                "schema": {
                  "$ref": "#/components/schemas/Experience"
                }
              },
              "application/json": {
                "schema": {
                  "$ref": "#/components/schemas/Experience"
                }
              },
              "text/json": {
                "schema": {
                  "$ref": "#/components/schemas/Experience"
                }
              }
            }
          }
        }
      },
      "put": {
        "tags": [
          "Experiences"
        ],
        "parameters": [
          {
            "name": "id",
            "in": "path",
            "required": true,
            "schema": {
              "type": "integer",
              "format": "int32"
            }
          }
        ],
        "requestBody": {
          "content": {
            "application/json": {
              "schema": {
                "$ref": "#/components/schemas/Experience"
              }
            },
            "text/json": {
              "schema": {
                "$ref": "#/components/schemas/Experience"
              }
            },
            "application/*+json": {
              "schema": {
                "$ref": "#/components/schemas/Experience"
              }
            }
          }
        },
        "responses": {
          "200": {
            "description": "OK"
          }
        }
      },
      "delete": {
        "tags": [
          "Experiences"
        ],
        "parameters": [
          {
            "name": "id",
            "in": "path",
            "required": true,
            "schema": {
              "type": "integer",
              "format": "int32"
            }
          }
        ],
        "responses": {
          "200": {
            "description": "OK"
          }
        }
      }
    },
    "/api/Projects": {
      "get": {
        "tags": [
          "Projects"
        ],
        "responses": {
          "200": {
            "description": "OK",
            "content": {
              "text/plain": {
                "schema": {
                  "type": "array",
                  "items": {
                    "$ref": "#/components/schemas/Project"
                  }
                }
              },
              "application/json": {
                "schema": {
                  "type": "array",
                  "items": {
                    "$ref": "#/components/schemas/Project"
                  }
                }
              },
              "text/json": {
                "schema": {
                  "type": "array",
                  "items": {
                    "$ref": "#/components/schemas/Project"
                  }
                }
              }
            }
          }
        }
      },
      "post": {
        "tags": [
          "Projects"
        ],
        "requestBody": {
          "content": {
            "application/json": {
              "schema": {
                "$ref": "#/components/schemas/Project"
              }
            },
            "text/json": {
              "schema": {
                "$ref": "#/components/schemas/Project"
              }
            },
            "application/*+json": {
              "schema": {
                "$ref": "#/components/schemas/Project"
              }
            }
          }
        },
        "responses": {
          "200": {
            "description": "OK",
            "content": {
              "text/plain": {
                "schema": {
                  "$ref": "#/components/schemas/Project"
                }
              },
              "application/json": {
                "schema": {
                  "$ref": "#/components/schemas/Project"
                }
              },
              "text/json": {
                "schema": {
                  "$ref": "#/components/schemas/Project"
                }
              }
            }
          }
        }
      }
    },
    "/api/Projects/{id}": {
      "get": {
        "tags": [
          "Projects"
        ],
        "parameters": [
          {
            "name": "id",
            "in": "path",
            "required": true,
            "schema": {
              "type": "integer",
              "format": "int32"
            }
          }
        ],
        "responses": {
          "200": {
            "description": "OK",
            "content": {
              "text/plain": {
                "schema": {
                  "$ref": "#/components/schemas/Project"
                }
              },
              "application/json": {
                "schema": {
                  "$ref": "#/components/schemas/Project"
                }
              },
              "text/json": {
                "schema": {
                  "$ref": "#/components/schemas/Project"
                }
              }
            }
          }
        }
      },
      "put": {
        "tags": [
          "Projects"
        ],
        "parameters": [
          {
            "name": "id",
            "in": "path",
            "required": true,
            "schema": {
              "type": "integer",
              "format": "int32"
            }
          }
        ],
        "requestBody": {
          "content": {
            "application/json": {
              "schema": {
                "$ref": "#/components/schemas/Project"
              }
            },
            "text/json": {
              "schema": {
                "$ref": "#/components/schemas/Project"
              }
            },
            "application/*+json": {
              "schema": {
                "$ref": "#/components/schemas/Project"
              }
            }
          }
        },
        "responses": {
          "200": {
            "description": "OK"
          }
        }
      },
      "delete": {
        "tags": [
          "Projects"
        ],
        "parameters": [
          {
            "name": "id",
            "in": "path",
            "required": true,
            "schema": {
              "type": "integer",
              "format": "int32"
            }
          }
        ],
        "responses": {
          "200": {
            "description": "OK"
          }
        }
      }
    },
    "/api/Skills": {
      "get": {
        "tags": [
          "Skills"
        ],
        "responses": {
          "200": {
            "description": "OK",
            "content": {
              "text/plain": {
                "schema": {
                  "type": "array",
                  "items": {
                    "$ref": "#/components/schemas/Skill"
                  }
                }
              },
              "application/json": {
                "schema": {
                  "type": "array",
                  "items": {
                    "$ref": "#/components/schemas/Skill"
                  }
                }
              },
              "text/json": {
                "schema": {
                  "type": "array",
                  "items": {
                    "$ref": "#/components/schemas/Skill"
                  }
                }
              }
            }
          }
        }
      },
      "post": {
        "tags": [
          "Skills"
        ],
        "requestBody": {
          "content": {
            "application/json": {
              "schema": {
                "$ref": "#/components/schemas/Skill"
              }
            },
            "text/json": {
              "schema": {
                "$ref": "#/components/schemas/Skill"
              }
            },
            "application/*+json": {
              "schema": {
                "$ref": "#/components/schemas/Skill"
              }
            }
          }
        },
        "responses": {
          "200": {
            "description": "OK",
            "content": {
              "text/plain": {
                "schema": {
                  "$ref": "#/components/schemas/Skill"
                }
              },
              "application/json": {
                "schema": {
                  "$ref": "#/components/schemas/Skill"
                }
              },
              "text/json": {
                "schema": {
                  "$ref": "#/components/schemas/Skill"
                }
              }
            }
          }
        }
      }
    },
    "/api/Skills/{id}": {
      "get": {
        "tags": [
          "Skills"
        ],
        "parameters": [
          {
            "name": "id",
            "in": "path",
            "required": true,
            "schema": {
              "type": "integer",
              "format": "int32"
            }
          }
        ],
        "responses": {
          "200": {
            "description": "OK",
            "content": {
              "text/plain": {
                "schema": {
                  "$ref": "#/components/schemas/Skill"
                }
              },
              "application/json": {
                "schema": {
                  "$ref": "#/components/schemas/Skill"
                }
              },
              "text/json": {
                "schema": {
                  "$ref": "#/components/schemas/Skill"
                }
              }
            }
          }
        }
      },
      "put": {
        "tags": [
          "Skills"
        ],
        "parameters": [
          {
            "name": "id",
            "in": "path",
            "required": true,
            "schema": {
              "type": "integer",
              "format": "int32"
            }
          }
        ],
        "requestBody": {
          "content": {
            "application/json": {
              "schema": {
                "$ref": "#/components/schemas/Skill"
              }
            },
            "text/json": {
              "schema": {
                "$ref": "#/components/schemas/Skill"
              }
            },
            "application/*+json": {
              "schema": {
                "$ref": "#/components/schemas/Skill"
              }
            }
          }
        },
        "responses": {
          "200": {
            "description": "OK"
          }
        }
      },
      "delete": {
        "tags": [
          "Skills"
        ],
        "parameters": [
          {
            "name": "id",
            "in": "path",
            "required": true,
            "schema": {
              "type": "integer",
              "format": "int32"
            }
          }
        ],
        "responses": {
          "200": {
            "description": "OK"
          }
        }
      }
    },
    "/WeatherForecast": {
      "get": {
        "tags": [
          "WeatherForecast"
        ],
        "operationId": "GetWeatherForecast",
        "responses": {
          "200": {
            "description": "OK",
            "content": {
              "text/plain": {
                "schema": {
                  "type": "array",
                  "items": {
                    "$ref": "#/components/schemas/WeatherForecast"
                  }
                }
              },
              "application/json": {
                "schema": {
                  "type": "array",
                  "items": {
                    "$ref": "#/components/schemas/WeatherForecast"
                  }
                }
              },
              "text/json": {
                "schema": {
                  "type": "array",
                  "items": {
                    "$ref": "#/components/schemas/WeatherForecast"
                  }
                }
              }
            }
          }
        }
      }
    }
  },
  "components": {
    "schemas": {
      "ContactMessage": {
        "type": "object",
        "properties": {
          "id": {
            "type": "integer",
            "format": "int32"
          },
          "name": {
            "type": "string",
            "nullable": true
          },
          "email": {
            "type": "string",
            "nullable": true
          },
          "subject": {
            "type": "string",
            "nullable": true
          },
          "message": {
            "type": "string",
            "nullable": true
          },
          "sentDate": {
            "type": "string",
            "format": "date-time"
          }
        },
        "additionalProperties": false
      },
      "Education": {
        "type": "object",
        "properties": {
          "id": {
            "type": "integer",
            "format": "int32"
          },
          "degree": {
            "type": "string",
            "nullable": true
          },
          "institution": {
            "type": "string",
            "nullable": true
          },
          "startDate": {
            "type": "string",
            "format": "date-time"
          },
          "endDate": {
            "type": "string",
            "format": "date-time"
          },
          "grade": {
            "type": "string",
            "nullable": true
          }
        },
        "additionalProperties": false
      },
      "Experience": {
        "type": "object",
        "properties": {
          "id": {
            "type": "integer",
            "format": "int32"
          },
          "company": {
            "type": "string",
            "nullable": true
          },
          "role": {
            "type": "string",
            "nullable": true
          },
          "description": {
            "type": "string",
            "nullable": true
          },
          "startDate": {
            "type": "string",
            "format": "date-time"
          },
          "endDate": {
            "type": "string",
            "format": "date-time",
            "nullable": true
          },
          "isCurrent": {
            "type": "boolean"
          }
        },
        "additionalProperties": false
      },
      "Project": {
        "type": "object",
        "properties": {
          "id": {
            "type": "integer",
            "format": "int32"
          },
          "title": {
            "type": "string",
            "nullable": true
          },
          "description": {
            "type": "string",
            "nullable": true
          },
          "technologies": {
            "type": "string",
            "nullable": true
          },
          "gitHubUrl": {
            "type": "string",
            "nullable": true
          },
          "liveDemoUrl": {
            "type": "string",
            "nullable": true
          },
          "imageUrl": {
            "type": "string",
            "nullable": true
          },
          "createdDate": {
            "type": "string",
            "format": "date-time"
          }
        },
        "additionalProperties": false
      },
      "Skill": {
        "type": "object",
        "properties": {
          "id": {
            "type": "integer",
            "format": "int32"
          },
          "name": {
            "type": "string",
            "nullable": true
          },
          "proficiency": {
            "type": "integer",
            "format": "int32"
          },
          "category": {
            "type": "string",
            "nullable": true
          }
        },
        "additionalProperties": false
      },
      "WeatherForecast": {
        "type": "object",
        "properties": {
          "date": {
            "type": "string",
            "format": "date"
          },
          "temperatureC": {
            "type": "integer",
            "format": "int32"
          },
          "temperatureF": {
            "type": "integer",
            "format": "int32",
            "readOnly": true
          },
          "summary": {
            "type": "string",
            "nullable": true
          }
        },
        "additionalProperties": false
      }
    }
  }
}